showroom/__init__.py
showroom/models/__init__.py
showroom/models/models.py
showroom-0.1.dist-info/METADATA
showroom-0.1.dist-info/WHEEL
showroom-0.1.dist-info/top_level.txt
showroom-0.1.dist-info/RECORD
