Metadata-Version: 2.1
Name: showroom
Version: 0.1
Summary: Ntt Showroom models and schemas
Home-page: 
Author: Ntt Backend Team
Author-email: lucassilluzio@gmail.com
License: MIT
Keywords: package ntt development
Classifier: License :: OSI Approved :: MIT License
Classifier: Programming Language :: Python :: 3.10
Classifier: Operating System :: OS Independent
Requires-Python: >=3.10
Requires-Dist: PyMySQL ==1.1.0
Requires-Dist: SQLAlchemy ==2.0.28
Provides-Extra: dev
Requires-Dist: pytest >=7.0 ; extra == 'dev'
Requires-Dist: twine >=4.0.2 ; extra == 'dev'
